social_sdk_testing_alpha_ti/__init__.py
social_sdk_testing_alpha_ti/api_client.py
social_sdk_testing_alpha_ti/api_response.py
social_sdk_testing_alpha_ti/configuration.py
social_sdk_testing_alpha_ti/exceptions.py
social_sdk_testing_alpha_ti/py.typed
social_sdk_testing_alpha_ti/rest.py
social_sdk_testing_alpha_ti/api/__init__.py
social_sdk_testing_alpha_ti/api/brand_api.py
social_sdk_testing_alpha_ti/api/default_api.py
social_sdk_testing_alpha_ti/api/generation_api.py
social_sdk_testing_alpha_ti/api/healthcheck_api.py
social_sdk_testing_alpha_ti/api/prompt_api.py
social_sdk_testing_alpha_ti/api/source_api.py
social_sdk_testing_alpha_ti/api/swagger_api.py
social_sdk_testing_alpha_ti/api/swaggers_api.py
social_sdk_testing_alpha_ti/api/tenant_api.py
social_sdk_testing_alpha_ti/api/worker_api.py
social_sdk_testing_alpha_ti/models/__init__.py
social_sdk_testing_alpha_ti/models/brand_compass_progress_schema.py
social_sdk_testing_alpha_ti/models/brand_compass_response_schema.py
social_sdk_testing_alpha_ti/models/brand_create_schema.py
social_sdk_testing_alpha_ti/models/brand_response_schema.py
social_sdk_testing_alpha_ti/models/brand_update_schema.py
social_sdk_testing_alpha_ti/models/generation_create_schema.py
social_sdk_testing_alpha_ti/models/generation_response_schema.py
social_sdk_testing_alpha_ti/models/prompt_create_schema.py
social_sdk_testing_alpha_ti/models/prompt_response_schema.py
social_sdk_testing_alpha_ti/models/prompt_update_schema.py
social_sdk_testing_alpha_ti/models/source_response_schema.py
social_sdk_testing_alpha_ti/models/tenant_create_schema.py
social_sdk_testing_alpha_ti/models/tenant_response_schema.py
social_sdk_testing_alpha_ti/models/tenant_settings_schema.py
social_sdk_testing_alpha_ti/models/tenant_update_schema.py
social_sdk_testing_alpha_ti/models/worker_create_schema.py
social_sdk_testing_alpha_ti/models/worker_response_schema.py
social_sdk_testing_alpha_ti/models/worker_update_schema.py
social_sdk_testing_alpha_ti-0.0.1.dist-info/METADATA
social_sdk_testing_alpha_ti-0.0.1.dist-info/WHEEL
social_sdk_testing_alpha_ti-0.0.1.dist-info/top_level.txt
social_sdk_testing_alpha_ti-0.0.1.dist-info/RECORD
